AUTHORS
ChangeLog
LICENSE
README.md
requirements.txt
setup.cfg
setup.py
yapot/__init__.py
yapot/cli.py
yapot/img-conv.py
yapot/yapot.py
yapot/yapot_utils.py
yapot.egg-info/PKG-INFO
yapot.egg-info/SOURCES.txt
yapot.egg-info/dependency_links.txt
yapot.egg-info/entry_points.txt
yapot.egg-info/not-zip-safe
yapot.egg-info/pbr.json
yapot.egg-info/requires.txt
yapot.egg-info/top_level.txt