Metadata-Version: 1.1
Name: yapot
Version: 0.4.0
Summary: Yet Another PDF OCR Tool
Home-page: UNKNOWN
Author: Timothy Duffy
Author-email: tim@timduffy.me
License: GPLv3+
Keywords: pdf
Platform: UNKNOWN
Classifier: Development Status :: 3 - Alpha
Classifier: Natural Language :: English
Classifier: Operating System :: POSIX :: Linux
Classifier: Programming Language :: Python :: 2.7
Classifier: Intended Audience :: Developers
